{
    "background": {
        "id": 0,
        "img": null,
        "bgColor": "BG_MAIN_DARK",
        "tile": {
            "color": "BG_MAIN_PATTERN_DARK",
            "num": [ 14, 10 ]
        },
        "isDrawGrid": false
    },
    "nodes": [
        {
            "component": "top_bg"
        },
        {
            "component": "top"
        },
        {
            "component": "bottom"
        },
        {
            "component": "levelup"
        },
        {
            "id": 100,
            "comment": "road map",
            "dimension": [ 0, 1, 18, 6 ],
            "margin": [ 10, 20 ],
            "innerMargin": [ 0, 0 ],
            "gridSize": [ 14, 7 ],
            "img": "",
            "color": [ "PURPLE", "BLUE" ],
            "objects": [
                {
                    "id": 99,
                    "position": [0, 0],
                    "span": [14, 6],
                    "align": "center",
                    "type": "layer"
                },
                {
                    "id": 101,
                    "position": [ 0, 5 ],
                    "alignment": "center",
                    "type": "layer"
                },
                {
                    "id": 102,
                    "position": [ 1, 5 ],
                    "alignment": "center",
                    "type": "layer"
                },
                {
                    "id": 103,
                    "position": [ 2, 4 ],
                    "alignment": "center",
                    "type": "layer"
                },
                {
                    "id": 104,
                    "position": [ 3, 4 ],
                    "alignment": "center",
                    "type": "layer"
                },
                {
                    "id": 105,
                    "position": [ 4, 4 ],
                    "alignment": "center",
                    "type": "layer"
                },
                {
                    "id": 106,
                    "position": [ 5, 3 ],
                    "alignment": "center",
                    "type": "layer"
                },
                {
                    "id": 107,
                    "position": [ 6, 3 ],
                    "alignment": "center",
                    "type": "layer"
                },
                {
                    "id": 108,
                    "position": [ 7, 3 ],
                    "alignment": "center",
                    "type": "layer"
                },
                {
                    "id": 109,
                    "position": [ 8, 2 ],
                    "alignment": "center",
                    "type": "layer"
                },
                {
                    "id": 110,
                    "position": [ 9, 2 ],
                    "alignment": "center",
                    "type": "layer"
                },
                {
                    "id": 111,
                    "position": [ 10, 2 ],
                    "alignment": "center",
                    "type": "layer"
                },
                {
                    "id": 112,
                    "position": [ 11, 1 ],
                    "alignment": "center",
                    "type": "layer"
                },
                {
                    "id": 113,
                    "position": [ 12, 1 ],
                    "alignment": "center",
                    "type": "layer"
                },
                {
                    "id": 114,
                    "position": [ 13, 1 ],
                    "alignment": "center",
                    "type": "layer"
                }
            ]
        },
        {
            "comment": "title",
            "dimension": [ 0, 1, 1, 3 ],
            "margin": [ 20, 20 ],
            "innerMargin": [ 0, 0 ],
            "gridSize": [ 1, 1 ],
            "color": 0,
            "objects": [
                {
                    "position": [0, 0],
                    "type": "label",
                    "alignment": "left",
                    "text": "ARCADE MODE",
                    "color": "WHITE_OPACITY_DEEP",
                    "fontSize": -2
                }
            ]
        }
    ]
}
